smseventlog/__init__.py
smseventlog/database.py
smseventlog/eventlog.py
smseventlog/factorycampaign.py
smseventlog/folders.py
smseventlog/functions.py
smseventlog/userforms.py
smseventlog/data/config.yaml
smseventlog/data/db_secret.txt
smseventlog/data/images/SMS Icon.png
smseventlog-3.0.0a0.dist-info/LICENSE
smseventlog-3.0.0a0.dist-info/METADATA
smseventlog-3.0.0a0.dist-info/WHEEL
smseventlog-3.0.0a0.dist-info/top_level.txt
smseventlog-3.0.0a0.dist-info/RECORD
